{
	"name": "FastFail",
	"author": "BeatMods Import",
	"description": "Shortens the \"Level Failed\" animation by ~2 seconds. Optionally lets you skip the animation via...",
	"subscribeUrl": "https://raw.githubusercontent.com/MicroCBer/BeatModsLithiumSource/main/BeatModsSource/beatmods.lithium.source.json",
	"versions": [
		{
			"version": "1.1.2",
			"downloads": {
				"universal": "https://beatmods.com/cdn/mod/cab50bf5b5cd2d39467714ef6a512180.zip"
			},
			"requiredGameVersion": "~1.11.0",
			"dependencies": []
		},
		{
			"version": "2.0.1",
			"downloads": {
				"universal": "https://beatmods.com/cdn/mod/fe1cee547b2bd3fc7d9dad5b55aee33f.zip"
			},
			"requiredGameVersion": "~1.12.2",
			"dependencies": []
		},
		{
			"version": "2.0.0",
			"downloads": {
				"universal": "https://beatmods.com/cdn/mod/682532b612d85eb0d5ef6ba614e9b14c.zip"
			},
			"requiredGameVersion": "~1.12.2",
			"dependencies": []
		},
		{
			"version": "2.0.2",
			"downloads": {
				"universal": "https://beatmods.com/cdn/mod/d71539c6884bc79fdaf6d8ca6c533568.zip"
			},
			"requiredGameVersion": "~1.13.2",
			"dependencies": []
		},
		{
			"version": "2.0.3",
			"downloads": {
				"universal": "https://beatmods.com/cdn/mod/fa7fc326ff9034c659b4d621383c8f5f.zip"
			},
			"requiredGameVersion": "~1.13.4",
			"dependencies": []
		},
		{
			"version": "2.0.4",
			"downloads": {
				"universal": "https://beatmods.com/cdn/mod/069f38c126e0f4de8d27ea5dd6a0b0f4.zip"
			},
			"requiredGameVersion": "~1.16.1",
			"dependencies": []
		},
		{
			"version": "2.0.5",
			"downloads": {
				"universal": "https://beatmods.com/cdn/mod/100274d221de75ce39bd4f2dd48c2ec9.zip"
			},
			"requiredGameVersion": "~1.16.3",
			"dependencies": []
		},
		{
			"version": "1.1.1",
			"downloads": {
				"universal": "https://beatmods.com/cdn/mod/9279c713cd233aab98a73b12a0907769.zip"
			},
			"requiredGameVersion": "~1.8.0",
			"dependencies": []
		}
	]
}