{
	"name": "NoMissText",
	"author": "BeatMods Import",
	"description": "Simple mod that hides the flying text when a note is missed so you can hide how bad you really are.",
	"subscribeUrl": "https://raw.githubusercontent.com/MicroCBer/BeatModsLithiumSource/main/BeatModsSource/beatmods.lithium.source.json",
	"versions": [
		{
			"version": "1.4.4",
			"downloads": {
				"universal": "https://beatmods.com/cdn/mod/1533b6aa935145c4f9d532c721437e65.zip"
			},
			"requiredGameVersion": "~1.12.2",
			"dependencies": []
		},
		{
			"version": "1.4.5",
			"downloads": {
				"universal": "https://beatmods.com/cdn/mod/c883918e6de551da6af35445ab3497e7.zip"
			},
			"requiredGameVersion": "~1.13.2",
			"dependencies": []
		},
		{
			"version": "1.4.6",
			"downloads": {
				"universal": "https://beatmods.com/cdn/mod/2aab1cbb1d8c9898de7a3a840bca6087.zip"
			},
			"requiredGameVersion": "~1.13.4",
			"dependencies": []
		},
		{
			"version": "1.4.7",
			"downloads": {
				"universal": "https://beatmods.com/cdn/mod/fb1ee5c238ad3d8b9f76ee92d35e52af.zip"
			},
			"requiredGameVersion": "~1.16.1",
			"dependencies": []
		}
	]
}