{
	"name": "Note Cut Minimizer",
	"author": "BeatMods Import",
	"description": "Tweaks the note debris to make it way less obtrusive on maps with lots of notes. Also makes deb...",
	"subscribeUrl": "https://raw.githubusercontent.com/MicroCBer/BeatModsLithiumSource/main/BeatModsSource/beatmods.lithium.source.json",
	"versions": [
		{
			"version": "1.1.1",
			"downloads": {
				"universal": "https://beatmods.com/cdn/mod/ec3cf59275c41e840ecbfca1bf7e4793.zip"
			},
			"requiredGameVersion": "~1.6.0",
			"dependencies": []
		}
	]
}